jl_db_comp/__init__.py
jl_db_comp/_version.py
jl_db_comp/connections.py
jl_db_comp/routes.py
jl_db_comp/tests/__init__.py
jl_db_comp/tests/test_routes.py
jl_db_comp-0.1.9.data/data/etc/jupyter/jupyter_server_config.d/jl_db_comp.json
jl_db_comp-0.1.9.data/data/share/jupyter/labextensions/jl_db_comp/package.json
jl_db_comp-0.1.9.data/data/share/jupyter/labextensions/jl_db_comp/schemas/jl_db_comp/package.json.orig
jl_db_comp-0.1.9.data/data/share/jupyter/labextensions/jl_db_comp/schemas/jl_db_comp/plugin.json
jl_db_comp-0.1.9.data/data/share/jupyter/labextensions/jl_db_comp/static/171.d366980651e0db8d978c.js
jl_db_comp-0.1.9.data/data/share/jupyter/labextensions/jl_db_comp/static/728.6552504d5b9b27551bc5.js
jl_db_comp-0.1.9.data/data/share/jupyter/labextensions/jl_db_comp/static/remoteEntry.0415590cc33a10bfa617.js
jl_db_comp-0.1.9.data/data/share/jupyter/labextensions/jl_db_comp/static/style.js
jl_db_comp-0.1.9.data/data/share/jupyter/labextensions/jl_db_comp/static/third-party-licenses.json
jl_db_comp-0.1.9.data/data/share/jupyter/labextensions/jl_db_comp/install.json
jl_db_comp-0.1.9.dist-info/METADATA
jl_db_comp-0.1.9.dist-info/WHEEL
jl_db_comp-0.1.9.dist-info/licenses/LICENSE
jl_db_comp-0.1.9.dist-info/RECORD
