Metadata-Version: 2.4
Name: jl_db_comp
Version: 0.1.9
Summary: A JupyterLab extension to complete db queries in jupyterlab notebooks
Project-URL: Homepage, https://github.com/Ben-Herz/jl_db_completer
Project-URL: Bug Tracker, https://github.com/Ben-Herz/jl_db_completer/issues
Project-URL: Repository, https://github.com/Ben-Herz/jl_db_completer.git
Author-email: jl_db_completer <herzben@pm.me>
License: BSD 3-Clause License
License-File: LICENSE
Keywords: jupyter,jupyterlab,jupyterlab-extension
Classifier: Framework :: Jupyter
Classifier: Framework :: Jupyter :: JupyterLab
Classifier: Framework :: Jupyter :: JupyterLab :: 4
Classifier: Framework :: Jupyter :: JupyterLab :: Extensions
Classifier: Framework :: Jupyter :: JupyterLab :: Extensions :: Prebuilt
Classifier: License :: OSI Approved :: BSD License
Classifier: Programming Language :: Python
Classifier: Programming Language :: Python :: 3
Classifier: Programming Language :: Python :: 3.10
Classifier: Programming Language :: Python :: 3.11
Classifier: Programming Language :: Python :: 3.12
Classifier: Programming Language :: Python :: 3.13
Classifier: Programming Language :: Python :: 3.14
Requires-Python: >=3.10
Requires-Dist: jupyter-server<3,>=2.4.0
Requires-Dist: psycopg2-binary>=2.9.0
Provides-Extra: dev
Requires-Dist: jupyterlab>=4; extra == 'dev'
Provides-Extra: test
Requires-Dist: coverage; extra == 'test'
Requires-Dist: pytest; extra == 'test'
Requires-Dist: pytest-asyncio; extra == 'test'
Requires-Dist: pytest-cov; extra == 'test'
Requires-Dist: pytest-jupyter[server]>=0.6.0; extra == 'test'
